kwx/__init__.py
kwx/languages.py
kwx/model.py
kwx/topic_model.py
kwx/utils.py
kwx/visuals.py
kwx-1.0.2.dist-info/LICENSE.txt
kwx-1.0.2.dist-info/METADATA
kwx-1.0.2.dist-info/WHEEL
kwx-1.0.2.dist-info/top_level.txt
kwx-1.0.2.dist-info/RECORD
