Metadata-Version: 2.1
Name: kwx
Version: 1.0.2
Summary: BERT, LDA, and TFIDF based keyword extraction in Python
Home-page: https://github.com/andrewtavis/kwx
Author: Andrew Tavis McAllister
Author-email: andrew.t.mcallister@gmail.com
License: new BSD
Platform: UNKNOWN
Classifier: Development Status :: 5 - Production/Stable
Classifier: Intended Audience :: Developers
Classifier: Intended Audience :: Education
Classifier: Intended Audience :: Science/Research
Classifier: License :: OSI Approved :: BSD License
Classifier: Programming Language :: Python
Classifier: Programming Language :: Python :: 3
Classifier: Programming Language :: Python :: 3.6
Classifier: Programming Language :: Python :: 3.7
Classifier: Programming Language :: Python :: 3.8
Classifier: Operating System :: OS Independent
Requires-Dist: pytest-cov
Requires-Dist: numpy
Requires-Dist: xlrd
Requires-Dist: pandas
Requires-Dist: matplotlib
Requires-Dist: seaborn
Requires-Dist: stopwordsiso
Requires-Dist: gensim
Requires-Dist: pyldavis
Requires-Dist: wordcloud
Requires-Dist: nltk
Requires-Dist: spacy
Requires-Dist: emoji
Requires-Dist: googletrans
Requires-Dist: scikit-learn
Requires-Dist: keras
Requires-Dist: IPython
Requires-Dist: sentence-transformers
Requires-Dist: tqdm
Requires-Dist: defusedxml
